uxsimpp/analyzer.py
uxsimpp/__init__.py
uxsimpp/README.md
uxsimpp/utils.py
uxsimpp/trafficppy.cpython-39-darwin.so
uxsimpp/uxsimpp.py
uxsimpp/trafficpp/utils.h
uxsimpp/trafficpp/traffi.h
uxsimpp/trafficpp/README.md
uxsimpp/trafficpp/traffi.cpp
uxsimpp/trafficpp/bindings.cpp
uxsimpp-0.0.1.dist-info/RECORD
uxsimpp-0.0.1.dist-info/WHEEL
uxsimpp-0.0.1.dist-info/METADATA
uxsimpp-0.0.1.dist-info/licenses/LICENSE
