Metadata-Version: 2.2
Name: uxsimpp
Version: 0.0.1
Summary: UXsim++: Fast and simple traffic simulator for Python
Author-Email: Toru Seo <seo.t.aa@m.titech.ac.jp>
License: MIT
Classifier: Intended Audience :: Science/Research
Classifier: Programming Language :: Python :: 3
Classifier: Programming Language :: C++
Classifier: License :: OSI Approved :: MIT License
Classifier: Topic :: Scientific/Engineering
Requires-Python: >=3.9
Requires-Dist: numpy>=1.21.5
Requires-Dist: matplotlib>=3.5.2
Requires-Dist: pillow>=9.2.0
Requires-Dist: tqdm>=4.64.1
Requires-Dist: scipy>=1.9.1
Requires-Dist: pandas>=1.4.4
